fhir_starter/__init__.py
fhir_starter/audit_client.py
fhir_starter/audit_messages.py
hit_starter_on_fhir-0.1.3.dist-info/LICENSE
hit_starter_on_fhir-0.1.3.dist-info/METADATA
hit_starter_on_fhir-0.1.3.dist-info/WHEEL
hit_starter_on_fhir-0.1.3.dist-info/top_level.txt
hit_starter_on_fhir-0.1.3.dist-info/RECORD
