Metadata-Version: 2.1
Name: hit-starter-on-fhir
Version: 0.1.3
Summary: Health IT starter kit providing auditing, authn and authz using FHIR and OpenID Connect
Home-page: https://github.com/walkIT-nl/hit-starter-on-fhir
Author: WalkIT
Author-email: code@walkit.nl
License: MIT license
Keywords: hit-starter-on-fhir
Platform: UNKNOWN
Classifier: Development Status :: 2 - Pre-Alpha
Classifier: Intended Audience :: Developers
Classifier: License :: OSI Approved :: MIT License
Classifier: Natural Language :: English
Classifier: Programming Language :: Python :: 3
Classifier: Programming Language :: Python :: 3.6
Classifier: Programming Language :: Python :: 3.7
Classifier: Programming Language :: Python :: 3.8
Requires-Python: >=3.6
Requires-Dist: requests
Requires-Dist: dataclasses
Requires-Dist: fhir.resources (==6.0.0)
